{
    "version": "0.18.0",
    "architecture": {
        "32bit": {
            "url": "https://source.symbolic.software/verifpal/verifpal/uploads/9c51f9eb5a6de4704ea5461d1ce77324/verifpal_0.18.0_windows_386.zip",
            "bin": [
                "verifpal_0.18.0_windows_386/verifpal.exe"
            ],
            "hash": "09a821b059d3b0456d5964a656ab87a48955322def0f9380cbb2fa7b2e4d7060"
        },
        "64bit": {
            "url": "https://source.symbolic.software/verifpal/verifpal/uploads/60195d05540c4bc31da6aac2d8415a4a/verifpal_0.18.0_windows_amd64.zip",
            "bin": [
                "verifpal_0.18.0_windows_amd64/verifpal.exe"
            ],
            "hash": "745e9ff6beac3f5914eb24959b20ae14bac3755328177c291a9f8136e14be80a"
        }
    },
    "homepage": "https://verifpal.com",
    "license": "https://www.gnu.org/licenses/gpl-3.0.en.html",
    "description": "Cryptographic protocol analysis for students and engineers."
}