{
    "version": "0.13.2",
    "architecture": {
        "32bit": {
            "url": "https://source.symbolic.software/verifpal/verifpal/uploads/05fe00134353a2260317ad8c42e96baf/verifpal_0.13.2_windows_386.zip",
            "bin": [
                "verifpal_0.13.2_windows_386/verifpal.exe"
            ],
            "hash": "b475a77b0cb9a788048af7cafd92b24eb529aa52a0cb78e45d2afc5cf5dc560f"
        },
        "64bit": {
            "url": "https://source.symbolic.software/verifpal/verifpal/uploads/379c8861c63716ab92f93d1dc05eb180/verifpal_0.13.2_windows_amd64.zip",
            "bin": [
                "verifpal_0.13.2_windows_amd64/verifpal.exe"
            ],
            "hash": "cd8e8846f4c76fc3973f7b5968d7ba3860df68cdd4629178b15d87e4708bd14b"
        }
    },
    "homepage": "https://verifpal.com",
    "license": "https://www.gnu.org/licenses/gpl-3.0.en.html",
    "description": "Cryptographic protocol analysis for students and engineers."
}