{
    "version": "0.14.7",
    "architecture": {
        "32bit": {
            "url": "https://source.symbolic.software/verifpal/verifpal/uploads/58817817faeba2f35ea6611594ece2e7/verifpal_0.14.7_windows_386.zip",
            "bin": [
                "verifpal_0.14.7_windows_386/verifpal.exe"
            ],
            "hash": "401ba5916cab45fc1e454ee11eada4c2286a837a9319d7ec08f01b2a4bf8f4d6"
        },
        "64bit": {
            "url": "https://source.symbolic.software/verifpal/verifpal/uploads/c17b1bbc5e4cbb0192c0a749ceaadae8/verifpal_0.14.7_windows_amd64.zip",
            "bin": [
                "verifpal_0.14.7_windows_amd64/verifpal.exe"
            ],
            "hash": "02be20de3f69a74caa8c601224c8d529f49371d89b1fea0551161f438ff5f697"
        }
    },
    "homepage": "https://verifpal.com",
    "license": "https://www.gnu.org/licenses/gpl-3.0.en.html",
    "description": "Cryptographic protocol analysis for students and engineers."
}