{
    "version": "0.19.3",
    "architecture": {
        "64bit": {
            "url": "https://source.symbolic.software/verifpal/verifpal/uploads/cabf8a37d76b231cfe5568794fd7cf87/verifpal_0.19.3_windows_amd64.zip",
            "bin": [
                "verifpal_0.19.3_windows_amd64/verifpal.exe"
            ],
            "hash": "a92639cfd464db6750813d9fa8d55a7e815fc1a0a3326bf54e6f55a4b81875a8"
        }
    },
    "homepage": "https://verifpal.com",
    "license": "https://www.gnu.org/licenses/gpl-3.0.en.html",
    "description": "Cryptographic protocol analysis for students and engineers."
}